mehdashti_auth/__init__.py
mehdashti_auth/py.typed
mehdashti_auth/core/__init__.py
mehdashti_auth/core/password.py
mehdashti_auth/core/tokens.py
mehdashti_auth/dependencies/__init__.py
mehdashti_auth/dependencies/current_user.py
mehdashti_auth/services/__init__.py
mehdashti_auth/services/auth_service.py
mehdashti_auth_kit-0.2.0.dist-info/METADATA
mehdashti_auth_kit-0.2.0.dist-info/WHEEL
mehdashti_auth_kit-0.2.0.dist-info/RECORD
