Metadata-Version: 2.4
Name: mehdashti-auth-kit
Version: 0.2.0
Summary: Authentication utilities for Smart Platform - JWT, password hashing, and auth services
Project-URL: Homepage, https://github.com/mehdashti/smart-platform
Project-URL: Repository, https://github.com/mehdashti/smart-platform.git
Project-URL: Issues, https://github.com/mehdashti/smart-platform/issues
Author: mehdashti
License: MIT
Keywords: authentication,fastapi,jwt,oauth,password-hashing
Classifier: Development Status :: 4 - Beta
Classifier: Framework :: FastAPI
Classifier: Intended Audience :: Developers
Classifier: License :: OSI Approved :: MIT License
Classifier: Programming Language :: Python :: 3
Classifier: Programming Language :: Python :: 3.13
Requires-Python: >=3.13
Requires-Dist: fastapi>=0.115.0
Requires-Dist: loguru>=0.7.2
Requires-Dist: passlib[argon2]>=1.7.4
Requires-Dist: pydantic-settings>=2.6.0
Requires-Dist: pydantic>=2.10.0
Requires-Dist: python-jose[cryptography]>=3.3.0
Provides-Extra: dev
Requires-Dist: pytest-asyncio>=0.24.0; extra == 'dev'
Requires-Dist: pytest>=8.0.0; extra == 'dev'
Requires-Dist: ruff>=0.8.0; extra == 'dev'
